Metadata-Version: 2.1
Name: pkgmod
Version: 0.0.1
Summary: Get module names from installed package names and back
Home-page: https://github.com/Mikata-Project/pkgmod
Author: NAGY, Attila
Author-email: nagy.attila@gmail.com
License: UNKNOWN
Platform: UNKNOWN
Classifier: Programming Language :: Python
Classifier: License :: OSI Approved :: MIT License
Classifier: Operating System :: OS Independent
